juka_kernel/__init__.py
juka_kernel/__main__.py
juka_kernel/install.py
juka_kernel/kernel.py
juka_kernel-0.2.dist-info/LICENSE
juka_kernel-0.2.dist-info/METADATA
juka_kernel-0.2.dist-info/WHEEL
juka_kernel-0.2.dist-info/top_level.txt
juka_kernel-0.2.dist-info/RECORD
