Metadata-Version: 2.1
Name: juka-kernel
Version: 0.2
Summary: Juka kernel for Jupyter
Home-page: https://github.com/jukaLang/juka_kernel
Author: Juka
Author-email: admin@jukalang.com
Classifier: License :: OSI Approved :: BSD License
Classifier: Development Status :: 2 - Pre-Alpha
License-File: LICENSE
Requires-Dist: jupyter-client
Requires-Dist: IPython
Requires-Dist: ipykernel
